libname/__init__.py
libname/hello.py
rithwikchhugani-0.0.1.dist-info/METADATA
rithwikchhugani-0.0.1.dist-info/WHEEL
rithwikchhugani-0.0.1.dist-info/top_level.txt
rithwikchhugani-0.0.1.dist-info/RECORD
