Metadata-Version: 2.1
Name: rithwikchhugani
Version: 0.0.1
Summary: hello package
Home-page: UNKNOWN
Author: Rithwik Chhugani
Author-email: <rithwikchhugani@gmail.com>
License: UNKNOWN
Keywords: hello
Platform: UNKNOWN
Classifier: Development Status :: 1 - Planning
Classifier: Intended Audience :: Developers
Classifier: Programming Language :: Python :: 3
Classifier: Operating System :: Unix
Classifier: Operating System :: MacOS :: MacOS X
Classifier: Operating System :: Microsoft :: Windows
